[
    {
        "title":"Polera Punisher",
        "description":"Camiseta The Punisher estampado en alta calidad directo en la tela",
        "price":19.9,
        "stock":29,
        "code":"A123",
        "thumbnail":[],
        "id":"3082afa6805ab2da0704"
    },

    {
        "title":"Polera Marvel",
        "description":"Polera Estampada, textil de alta calidad y durabilida.",
        "price":19.9,
        "stock":22,
        "code":"L123",
        "thumbnail":[],
        "id":"e6547430dc9766defa37"
    },

    {
        "title":"Anillo Punisher",
        "description":"Anillo Punisher Anillo Calavera Acero Titanium Descripción Anillo Acero Titanium",
        "price":9.9,
        "stock":10,
        "code":"Y243",
        "thumbnail":[],
        "id":"9ade1cfb73dcdad6d519"
    },

    {
        "title":"AzucarPin Marverl Dead Pool",
        "description":"100% nuevo Alta calidad Tipo de producto: Broche Material: aleación Metálica",
        "price":9.9,
        "stock":14,
        "code":"A433",
        "thumbnail":[],
        "id":"3ac05872b4643be34d9d"
    }
]